{"file":"chongmingniao_bianyi_idle.png","frames":{
"idle_1_body_00":{"x":414,"y":0,"w":204,"h":245,"offX":116,"offY":0,"sourceW":320,"sourceH":320},
"idle_1_body_01":{"x":620,"y":0,"w":204,"h":244,"offX":116,"offY":0,"sourceW":320,"sourceH":320},
"idle_1_body_02":{"x":0,"y":247,"w":204,"h":244,"offX":116,"offY":0,"sourceW":320,"sourceH":320},
"idle_1_body_03":{"x":207,"y":0,"w":205,"h":244,"offX":115,"offY":0,"sourceW":320,"sourceH":320},
"idle_1_body_04":{"x":207,"y":246,"w":205,"h":243,"offX":115,"offY":0,"sourceW":320,"sourceH":320},
"idle_1_body_05":{"x":206,"y":491,"w":205,"h":241,"offX":115,"offY":0,"sourceW":320,"sourceH":320},
"idle_1_body_06":{"x":0,"y":0,"w":205,"h":245,"offX":115,"offY":0,"sourceW":320,"sourceH":320},
"idle_1_body_07":{"x":620,"y":246,"w":204,"h":244,"offX":116,"offY":0,"sourceW":320,"sourceH":320},
"idle_3_body_00":{"x":0,"y":1202,"w":205,"h":231,"offX":0,"offY":0,"sourceW":320,"sourceH":320},
"idle_3_body_01":{"x":0,"y":734,"w":205,"h":232,"offX":0,"offY":0,"sourceW":320,"sourceH":320},
"idle_3_body_02":{"x":0,"y":968,"w":205,"h":232,"offX":0,"offY":0,"sourceW":320,"sourceH":320},
"idle_3_body_03":{"x":413,"y":492,"w":206,"h":232,"offX":0,"offY":0,"sourceW":320,"sourceH":320},
"idle_3_body_04":{"x":621,"y":492,"w":206,"h":232,"offX":0,"offY":0,"sourceW":320,"sourceH":320},
"idle_3_body_05":{"x":413,"y":726,"w":206,"h":232,"offX":0,"offY":0,"sourceW":320,"sourceH":320},
"idle_3_body_06":{"x":621,"y":726,"w":206,"h":232,"offX":0,"offY":0,"sourceW":320,"sourceH":320},
"idle_3_body_07":{"x":0,"y":1435,"w":205,"h":231,"offX":0,"offY":0,"sourceW":320,"sourceH":320},
"idle_5_body_00":{"x":207,"y":1212,"w":165,"h":210,"offX":39,"offY":25,"sourceW":320,"sourceH":320},
"idle_5_body_01":{"x":374,"y":1212,"w":162,"h":213,"offX":42,"offY":22,"sourceW":320,"sourceH":320},
"idle_5_body_02":{"x":414,"y":247,"w":166,"h":214,"offX":39,"offY":21,"sourceW":320,"sourceH":320},
"idle_5_body_03":{"x":540,"y":1176,"w":165,"h":214,"offX":40,"offY":21,"sourceW":320,"sourceH":320},
"idle_5_body_04":{"x":0,"y":493,"w":167,"h":213,"offX":39,"offY":21,"sourceW":320,"sourceH":320},
"idle_5_body_05":{"x":557,"y":960,"w":166,"h":211,"offX":39,"offY":21,"sourceW":320,"sourceH":320},
"idle_5_body_06":{"x":389,"y":960,"w":166,"h":214,"offX":39,"offY":21,"sourceW":320,"sourceH":320},
"idle_5_body_07":{"x":207,"y":997,"w":166,"h":213,"offX":39,"offY":22,"sourceW":320,"sourceH":320},
"idle_7_body_00":{"x":829,"y":526,"w":180,"h":261,"offX":114,"offY":10,"sourceW":320,"sourceH":320},
"idle_7_body_01":{"x":0,"y":1668,"w":179,"h":261,"offX":115,"offY":10,"sourceW":320,"sourceH":320},
"idle_7_body_02":{"x":207,"y":734,"w":180,"h":261,"offX":114,"offY":10,"sourceW":320,"sourceH":320},
"idle_7_body_03":{"x":829,"y":263,"w":180,"h":261,"offX":114,"offY":10,"sourceW":320,"sourceH":320},
"idle_7_body_04":{"x":826,"y":0,"w":181,"h":261,"offX":113,"offY":10,"sourceW":320,"sourceH":320},
"idle_7_body_05":{"x":181,"y":1668,"w":181,"h":251,"offX":113,"offY":11,"sourceW":320,"sourceH":320},
"idle_7_body_06":{"x":829,"y":789,"w":180,"h":261,"offX":114,"offY":10,"sourceW":320,"sourceH":320},
"idle_7_body_07":{"x":364,"y":1668,"w":174,"h":261,"offX":114,"offY":10,"sourceW":320,"sourceH":320}}}