{"file":"qinglong_fs_die.png","frames":{
"die_7_body_00":{"x":239,"y":502,"w":222,"h":222,"offX":222,"offY":160,"sourceW":640,"sourceH":640},
"die_7_body_01":{"x":0,"y":0,"w":257,"h":230,"offX":185,"offY":173,"sourceW":640,"sourceH":640},
"die_7_body_02":{"x":0,"y":502,"w":237,"h":217,"offX":205,"offY":159,"sourceW":640,"sourceH":640},
"die_7_body_03":{"x":0,"y":232,"w":232,"h":242,"offX":214,"offY":65,"sourceW":640,"sourceH":640},
"die_7_body_04":{"x":259,"y":0,"w":219,"h":262,"offX":217,"offY":48,"sourceW":640,"sourceH":640},
"die_7_body_05":{"x":234,"y":264,"w":224,"h":236,"offX":209,"offY":160,"sourceW":640,"sourceH":640},
"die_7_body_06":{"x":0,"y":721,"w":133,"h":104,"offX":285,"offY":283,"sourceW":640,"sourceH":640},
"die_7_body_07":{"x":460,"y":264,"w":26,"h":26,"offX":277,"offY":297,"sourceW":640,"sourceH":640}}}